pywas/__init__.py
pywas/cookiecutter_template/module_verilog/cookiecutter.json
pywas/cookiecutter_template/module_verilog/{{cookiecutter.project_slug}}/Makefile
pywas/cookiecutter_template/module_verilog/{{cookiecutter.project_slug}}/test_{{cookiecutter.project_slug}}.py
pywas/cookiecutter_template/module_verilog/{{cookiecutter.project_slug}}/{{cookiecutter.project_slug}}.md
pywas/cookiecutter_template/module_verilog/{{cookiecutter.project_slug}}/{{cookiecutter.project_slug}}.v
pywas/cookiecutter_template/openlane_project/cookiecutter.json
pywas/flow/openlane.yaml
pywas/jinja2_template/_tb.v
pywas/jinja2_template/char_mos.net
pywas/main.py
pywas/parse/__init__.py
pywas/parse/results.py
pywas/parse/spice3raw.py
pywas/template.py
pywas/wrapper/__init__.py
pywas/wrapper/base_wrapper.py
pywas/wrapper/ngspice.py
pywas-0.1.6.dist-info/entry_points.txt
pywas-0.1.6.dist-info/METADATA
pywas-0.1.6.dist-info/WHEEL
pywas-0.1.6.dist-info/RECORD
