Metadata-Version: 2.1
Name: pywas
Version: 0.1.6
Summary: 
Author: Patarimi
Author-email: mpqqch@gmail.com
Requires-Python: >=3.8,<4.0
Classifier: Programming Language :: Python :: 3
Classifier: Programming Language :: Python :: 3.8
Classifier: Programming Language :: Python :: 3.9
Classifier: Programming Language :: Python :: 3.10
Classifier: Programming Language :: Python :: 3.11
Requires-Dist: cookiecutter (>=2.1.1,<3.0.0)
Requires-Dist: h5py (>=3.7.0,<4.0.0)
Requires-Dist: jinja2 (>=3.1.2,<4.0.0)
Requires-Dist: numpy (>=1.23.2,<2.0.0)
Requires-Dist: pydantic (>=1.10.7,<2.0.0)
Requires-Dist: pyyaml (>=6.0,<7.0)
Requires-Dist: rich (>=13.3.3,<14.0.0)
Requires-Dist: typer (>=0.7.0,<0.8.0)
Requires-Dist: wget (>=3.2,<4.0)
